LICENSE
geld/__init__.py
geld/clients.py
geld/common/__init__.py
geld/common/constants.py
geld/common/decorators.py
geld/common/exceptions.py
geld/common/singleton.py
geld/common/validators.py
geld/sync/__init__.py
geld/sync/base.py
geld/sync/client.py
geld-0.3.0.dist-info/LICENSE
geld-0.3.0.dist-info/WHEEL
geld-0.3.0.dist-info/METADATA
geld-0.3.0.dist-info/RECORD
